pibooth_extra_lights.py
pibooth_extra_lights-1.0.2.dist-info/LICENSE
pibooth_extra_lights-1.0.2.dist-info/METADATA
pibooth_extra_lights-1.0.2.dist-info/WHEEL
pibooth_extra_lights-1.0.2.dist-info/entry_points.txt
pibooth_extra_lights-1.0.2.dist-info/top_level.txt
pibooth_extra_lights-1.0.2.dist-info/RECORD
